pptx2img/__init__.py
pptx2img/converter.py
tests/__init__.py
tests/test_converter.py
pptx2img-0.1.0.dist-info/LICENSE
pptx2img-0.1.0.dist-info/METADATA
pptx2img-0.1.0.dist-info/WHEEL
pptx2img-0.1.0.dist-info/top_level.txt
pptx2img-0.1.0.dist-info/RECORD
