Metadata-Version: 2.1
Name: pptx2img
Version: 0.1.0
Summary: This library helps in converting pptx slides to images using LibreOffice
Home-page: https://github.com/captainnarwal/pptx2img
Author: Neeraj Narwal
Author-email: neerajnarwal2000@gmail.com
License: MIT
Classifier: Programming Language :: Python :: 3
Classifier: License :: OSI Approved :: MIT License
Classifier: Operating System :: OS Independent
Requires-Python: >=3.6
License-File: LICENSE
